mmaze/__init__.py
mmaze/__main__.py
mmaze/cell.py
mmaze/maze.py
mmaze/visual.py
mmaze/generator/__init__.py
mmaze/generator/backtracking.py
mmaze/generator/base.py
mmaze/generator/binary_tree.py
mmaze/generator/division.py
mmaze/generator/ellers.py
mmaze/generator/growing_tree.py
mmaze/generator/hunt_and_kill.py
mmaze/generator/kruskal.py
mmaze/generator/prims.py
mmaze/generator/wilsons.py
mmaze/solver/__init__.py
mmaze/solver/backtracking.py
mmaze/solver/base.py
mmaze/solver/shortest_path.py
mmaze-0.1.4.dist-info/LICENSE
mmaze-0.1.4.dist-info/METADATA
mmaze-0.1.4.dist-info/WHEEL
mmaze-0.1.4.dist-info/top_level.txt
mmaze-0.1.4.dist-info/RECORD
