Metadata-Version: 2.1
Name: mmaze
Version: 0.1.4
Summary: Generating and solving maze
Home-page: https://github.com/MorvanZhou/mmaze
Author: MorvanZhou
Author-email: mofanpy@hotmail.com
Project-URL: Bug Tracker, https://github.com/MorvanZhou/mmaze/issues
Classifier: Programming Language :: Python :: 3
Classifier: License :: OSI Approved :: MIT License
Classifier: Operating System :: OS Independent
Requires-Python: >=3.6
License-File: LICENSE
Requires-Dist: dataclasses (>=0.8) ; python_version < "3.7"
Provides-Extra: build
Requires-Dist: tox (==3.24.3) ; extra == 'build'
Requires-Dist: build ; extra == 'build'
Requires-Dist: twine ; extra == 'build'
Requires-Dist: pylint ; extra == 'build'
Provides-Extra: test
Requires-Dist: matplotlib (>=3.3.4) ; extra == 'test'
